sharegpt_dataset/__init__.py
sharegpt_dataset/_access.py
sharegpt_dataset/data/ShareGPT_V3_unfiltered_cleaned_split.json
sharegpt_dataset-0.1.0.dist-info/METADATA
sharegpt_dataset-0.1.0.dist-info/WHEEL
sharegpt_dataset-0.1.0.dist-info/top_level.txt
sharegpt_dataset-0.1.0.dist-info/RECORD
