Metadata-Version: 2.4
Name: sharegpt-dataset
Version: 0.1.0
Summary: Local package containing the ShareGPT V3 unfiltered cleaned split dataset.
Classifier: Programming Language :: Python :: 3
Requires-Python: >=3.8
